UltrafastOpticsLectureNotesMit6977/README.md
UltrafastOpticsLectureNotesMit6977/__init__.py
UltrafastOpticsLectureNotesMit6977/__main__.py
UltrafastOpticsLectureNotesMit6977/file.pdf
UltrafastOpticsLectureNotesMit6977/index.html
ultrafast_optics_lecture_notes_mit_6_977-2024.3.2.0.dist-info/METADATA
ultrafast_optics_lecture_notes_mit_6_977-2024.3.2.0.dist-info/WHEEL
ultrafast_optics_lecture_notes_mit_6_977-2024.3.2.0.dist-info/entry_points.txt
ultrafast_optics_lecture_notes_mit_6_977-2024.3.2.0.dist-info/top_level.txt
ultrafast_optics_lecture_notes_mit_6_977-2024.3.2.0.dist-info/RECORD
